LICENSE
MANIFEST.in
README.md
setup.cfg
setup.py
agape/__init__.py
agape/models.py
agape/signals.py
agape/test.py
agape/viewsets.py
agape/authentication/__init__.py
agape/authentication/admin.py
agape/authentication/apps.py
agape/authentication/models.py
agape/authentication/permissions.py
agape/authentication/serializers.py
agape/authentication/settings.py
agape/authentication/tests.py
agape/authentication/urls.py
agape/authentication/views.py
agape/authentication/migrations/0001_initial.py
agape/authentication/migrations/__init__.py
agape/contacts/admin.py
agape/contacts/apps.py
agape/contacts/connector.py
agape/contacts/models.py
agape/contacts/permissions.py
agape/contacts/serializers.py
agape/contacts/tests.py
agape/contacts/urls.py
agape/contacts/views.py
agape/contacts/migrations/0001_initial.py
agape/contacts/migrations/__init__.py
agape/files/admin.py
agape/files/apps.py
agape/files/connector.py
agape/files/models.py
agape/files/permissions.py
agape/files/serializers.py
agape/files/tests.py
agape/files/urls.py
agape/files/views.py
agape/members/admin.py
agape/members/apps.py
agape/members/connector.py
agape/members/models.py
agape/members/permissions.py
agape/members/serializers.py
agape/members/tests.py
agape/members/urls.py
agape/members/views.py
agape/members/migrations/0001_initial.py
agape/members/migrations/__init__.py
agape/organizations/admin.py
agape/organizations/apps.py
agape/organizations/models.py
agape/organizations/permissions.py
agape/organizations/serializers.py
agape/organizations/tests.py
agape/organizations/urls.py
agape/organizations/views.py
agape/organizations/migrations/0001_initial.py
agape/organizations/migrations/0002_organization_description.py
agape/organizations/migrations/0003_auto_20180713_0012.py
agape/organizations/migrations/__init__.py
agape/people/admin.py
agape/people/apps.py
agape/people/models.py
agape/people/permissions.py
agape/people/serializers.py
agape/people/tests.py
agape/people/urls.py
agape/people/views.py
agape_django.egg-info/PKG-INFO
agape_django.egg-info/SOURCES.txt
agape_django.egg-info/dependency_links.txt
agape_django.egg-info/requires.txt
agape_django.egg-info/top_level.txt