Metadata-Version: 1.1
Name: agape-django
Version: 0.4.4
Summary: Collection of reusable Django Applications for Rapid Application Development
Home-page: https://github.com/codewiseio/agape-django
Author: Jeffrey Ray Hallock
Author-email: codewiseio@gmail.com
License: MIT License
Platform: UNKNOWN
Classifier: Environment :: Web Environment
Classifier: Framework :: Django
Classifier: Intended Audience :: Developers
Classifier: License :: OSI Approved :: MIT License
Classifier: Operating System :: OS Independent
Classifier: Programming Language :: Python
Classifier: Programming Language :: Python :: 3.4
Classifier: Programming Language :: Python :: 3.5
Classifier: Topic :: Internet :: WWW/HTTP
Classifier: Topic :: Internet :: WWW/HTTP :: Dynamic Content
